simplescreens.py
simplescreens-0.1.3.dist-info/LICENSE
simplescreens-0.1.3.dist-info/METADATA
simplescreens-0.1.3.dist-info/WHEEL
simplescreens-0.1.3.dist-info/top_level.txt
simplescreens-0.1.3.dist-info/RECORD
